rkdonate/__init__.py
rkdonate/rk.py
rkdonate-0.0.1.dist-info/METADATA
rkdonate-0.0.1.dist-info/WHEEL
rkdonate-0.0.1.dist-info/top_level.txt
rkdonate-0.0.1.dist-info/RECORD
